plasmodia/__init__.py
plasmodia/experiences/__init__.py
plasmodia/experiences/deques/__init__.py
plasmodia/experiences/deques/bases.py
plasmodia/experiences/deques/fifo.py
plasmodia/experiences/deques/uniform.py
plasmodia/experiences/interfaces/__init__.py
plasmodia/experiences/interfaces/experiences.py
plasmodia/experiences/list.py
plasmodia/fantasies/__init__.py
plasmodia/fantasies/interfaces/__init__.py
plasmodia/fantasies/interfaces/multi.py
plasmodia/fantasies/interfaces/simulations.py
plasmodia/fantasies/interfaces/single.py
plasmodia/games/__init__.py
plasmodia/games/gym/__init__.py
plasmodia/games/gym/makers.py
plasmodia/games/gym/parallel.py
plasmodia/games/gym/sequential.py
plasmodia/games/gym/single.py
plasmodia/games/gym/utils.py
plasmodia/games/interfaces/__init__.py
plasmodia/games/interfaces/interactive.py
plasmodia/games/interfaces/multi.py
plasmodia/games/interfaces/single.py
plasmodia/games/interfaces/specs/__init__.py
plasmodia/games/interfaces/specs/granularity.py
plasmodia/games/interfaces/specs/specs.py
plasmodia/games/wrappers/__init__.py
plasmodia/games/wrappers/independent.py
plasmodia/players/__init__.py
plasmodia/players/interfaces/__init__.py
plasmodia/players/interfaces/gamers.py
plasmodia/players/interfaces/multi/__init__.py
plasmodia/players/interfaces/multi/multi.py
plasmodia/players/interfaces/single.py
plasmodia/players/iterative/__init__.py
plasmodia/players/iterative/es/__init__.py
plasmodia/players/iterative/interfaces.py
plasmodia/players/iterative/rl/__init__.py
plasmodia/players/iterative/rl/interfaces.py
plasmodia/players/iterative/rl/offline/__init__.py
plasmodia/players/iterative/rl/offline/dqn/__init__.py
plasmodia/players/iterative/rl/offline/dqn/dqn.py
plasmodia/players/iterative/rl/online/__init__.py
plasmodia/players/iterative/rl/online/online.py
plasmodia/players/iterative/rl/online/ppo/__init__.py
plasmodia/players/iterative/rl/online/ppo/ppo.py
plasmodia/utils/__init__.py
plasmodia/utils/cmp.py
plasmodia-0.0.0.dist-info/LICENSE.md
plasmodia-0.0.0.dist-info/METADATA
plasmodia-0.0.0.dist-info/WHEEL
plasmodia-0.0.0.dist-info/RECORD
